aiida_aimall/__init__.py
aiida_aimall/calculations.py
aiida_aimall/controllers.py
aiida_aimall/data.py
aiida_aimall/parsers.py
aiida_aimall/workchains/__init__.py
aiida_aimall/workchains/calcfunctions.py
aiida_aimall/workchains/input.py
aiida_aimall/workchains/param_parts.py
aiida_aimall/workchains/qc_programs.py
aiida_aimall/workchains/subparam.py
aiida_aimall-1.0.5.dist-info/entry_points.txt
aiida_aimall-1.0.5.dist-info/licenses/LICENSE
aiida_aimall-1.0.5.dist-info/WHEEL
aiida_aimall-1.0.5.dist-info/METADATA
aiida_aimall-1.0.5.dist-info/RECORD
