Metadata-Version: 2.4
Name: aiida-aimall
Version: 1.0.5
Summary: A plugin to interface AIMAll with AiiDA
Keywords: aiida,plugin
Author-email: Kevin Lefrancois-Gagnon <kgagnon@lakeheadu.ca>
Requires-Python: >=3.10
Classifier: Programming Language :: Python
Classifier: Programming Language :: Python :: 3
Classifier: Programming Language :: Python :: 3.10
Classifier: Programming Language :: Python :: 3.11
Classifier: Intended Audience :: Science/Research
Classifier: License :: OSI Approved :: MIT License
Classifier: Natural Language :: English
Classifier: Development Status :: 3 - Alpha
Classifier: Framework :: AiiDA
License-File: LICENSE
Requires-Dist: aiida-core>=2.0,<3
Requires-Dist: pandas<2.2
Requires-Dist: voluptuous
Requires-Dist: aiida-submission-controller<0.2
Requires-Dist: pydantic
Requires-Dist: ase
Requires-Dist: cclib
Requires-Dist: multiprocess
Requires-Dist: subproptools
Requires-Dist: aiida-gaussian
Requires-Dist: pymatgen
Requires-Dist: aiida-shell
Requires-Dist: qc-iodata
Requires-Dist: numpy
Requires-Dist: sphinx ; extra == "docs"
Requires-Dist: sphinxcontrib-contentui ; extra == "docs"
Requires-Dist: sphinxcontrib-details-directive ; extra == "docs"
Requires-Dist: sphinx-copybutton~=0.5.2 ; extra == "docs"
Requires-Dist: sphinx-autoapi~=3.0.0 ; extra == "docs"
Requires-Dist: sphinx-design~=0.4.1 ; extra == "docs"
Requires-Dist: sphinx-click~=4.4.0 ; extra == "docs"
Requires-Dist: myst-parser~=1.0.0 ; extra == "docs"
Requires-Dist: sphinx-book-theme~=1.0.1 ; extra == "docs"
Requires-Dist: sphinxcontrib-details-directive~=0.1.0 ; extra == "docs"
Requires-Dist: nbsphinx ; extra == "docs"
Requires-Dist: sphinx-gallery ; extra == "docs"
Requires-Dist: ipykernel ; extra == "docs"
Requires-Dist: pre-commit~=2.2 ; extra == "pre-commit"
Requires-Dist: pylint ; extra == "pre-commit"
Requires-Dist: pgtest~=1.3.1 ; extra == "testing"
Requires-Dist: pytest~=6.0 ; extra == "testing"
Requires-Dist: pytest-cov ; extra == "testing"
Requires-Dist: pytest-regressions~=2.3 ; extra == "testing"
Requires-Dist: coveralls ; extra == "testing"
Requires-Dist: group_decomposition ; extra == "testing"
Project-URL: Documentation, https://aiida-aimall.readthedocs.io
Project-URL: Home, https://aiida-aimall.readthedocs.io
Project-URL: Source, https://github.com/kmlefran/aiida-aimall
Provides-Extra: docs
Provides-Extra: pre-commit
Provides-Extra: testing
